reuse_shortcuts/__init__.py
reuse_shortcuts/__main__.py
reuse_shortcuts/_version.py
reuse_shortcuts/py.typed
reuse_shortcuts-1.0.2.dist-info/licenses/LICENSES/CC-BY-4.0.txt
reuse_shortcuts-1.0.2.dist-info/licenses/LICENSES/CC0-1.0.txt
reuse_shortcuts-1.0.2.dist-info/licenses/LICENSES/GPL-3.0-or-later.txt
reuse_shortcuts-1.0.2.dist-info/METADATA
reuse_shortcuts-1.0.2.dist-info/WHEEL
reuse_shortcuts-1.0.2.dist-info/entry_points.txt
reuse_shortcuts-1.0.2.dist-info/top_level.txt
reuse_shortcuts-1.0.2.dist-info/RECORD
