Metadata-Version: 2.4
Name: reuse-shortcuts
Version: 1.0.2
Summary: Shortcuts Management for reuse license utility
Author-email: "Philipp S. Sommer" <philipp.sommer@hereon.de>
Maintainer-email: "Philipp S. Sommer" <philipp.sommer@hereon.de>
License: GPL-3.0-or-later
Project-URL: Homepage, https://codebase.helmholtz.cloud/hcdc/reuse-shortcuts
Project-URL: Documentation, https://reuse-shortcuts.readthedocs.io/en/latest/
Project-URL: Source, https://codebase.helmholtz.cloud/hcdc/reuse-shortcuts
Project-URL: Tracker, https://codebase.helmholtz.cloud/hcdc/reuse-shortcuts/issues/
Keywords: reuse,licenses
Classifier: Intended Audience :: Developers
Classifier: Operating System :: OS Independent
Classifier: Development Status :: 5 - Production/Stable
Classifier: Programming Language :: Python
Classifier: Programming Language :: Python :: 3
Classifier: Programming Language :: Python :: 3 :: Only
Classifier: Programming Language :: Python :: 3.9
Classifier: Programming Language :: Python :: 3.10
Classifier: Programming Language :: Python :: 3.11
Classifier: Programming Language :: Python :: 3.12
Classifier: Programming Language :: Python :: 3.13
Classifier: Programming Language :: Python :: 3.14
Classifier: Typing :: Typed
Requires-Python: >=3.9
License-File: LICENSES/CC-BY-4.0.txt
License-File: LICENSES/CC0-1.0.txt
License-File: LICENSES/GPL-3.0-or-later.txt
Requires-Dist: reuse
Requires-Dist: PyYAML
Provides-Extra: testsite
Requires-Dist: tox; extra == "testsite"
Requires-Dist: isort==5.12.0; extra == "testsite"
Requires-Dist: black==23.1.0; extra == "testsite"
Requires-Dist: blackdoc==0.3.8; extra == "testsite"
Requires-Dist: flake8==6.0.0; extra == "testsite"
Requires-Dist: pre-commit; extra == "testsite"
Requires-Dist: mypy; extra == "testsite"
Requires-Dist: pytest-cov; extra == "testsite"
Requires-Dist: reuse; extra == "testsite"
Requires-Dist: cffconvert; extra == "testsite"
Requires-Dist: GitPython; extra == "testsite"
Requires-Dist: types-PyYAML; extra == "testsite"
Provides-Extra: docs
Requires-Dist: autodocsumm; extra == "docs"
Requires-Dist: sphinx-rtd-theme; extra == "docs"
Requires-Dist: hereon-netcdf-sphinxext; extra == "docs"
Requires-Dist: sphinx-design; extra == "docs"
Requires-Dist: myst_parser; extra == "docs"
Requires-Dist: sphinx-click; extra == "docs"
Provides-Extra: dev
Requires-Dist: reuse-shortcuts[testsite]; extra == "dev"
Requires-Dist: reuse-shortcuts[docs]; extra == "dev"
Dynamic: license-file
